keybhook/LICENSE
keybhook/README.md
keybhook/__init__.py
keybhook/requirements.txt
keybhook/thirdparty.json
keybhook-0.10.dist-info/LICENSE.rst
keybhook-0.10.dist-info/METADATA
keybhook-0.10.dist-info/WHEEL
keybhook-0.10.dist-info/top_level.txt
keybhook-0.10.dist-info/RECORD
