Metadata-Version: 2.1
Name: keybhook
Version: 0.10
Summary: Just a little keylogger
Home-page: https://github.com/hansalemaos/keybhook
Author: Johannes Fischer
Author-email: aulasparticularesdealemaosp@gmail.com
License: MIT
Keywords: keylogger,keystroke,log
Classifier: Development Status :: 4 - Beta
Classifier: Programming Language :: Python :: 3 :: Only
Classifier: Programming Language :: Python :: 3.10
Classifier: Topic :: Software Development :: Libraries :: Python Modules
Classifier: Topic :: Utilities
License-File: LICENSE.rst
Requires-Dist: kthread
